streamlit_kpi/__init__.py
streamlit_kpi/frontend/index.html
streamlit_kpi/frontend/main.js
streamlit_kpi/frontend/streamlit-component-lib.js
streamlit_kpi/frontend/style.css
streamlit_kpi-0.0.36.dist-info/LICENSE
streamlit_kpi-0.0.36.dist-info/METADATA
streamlit_kpi-0.0.36.dist-info/WHEEL
streamlit_kpi-0.0.36.dist-info/top_level.txt
streamlit_kpi-0.0.36.dist-info/RECORD
