Metadata-Version: 2.1
Name: streamlit-kpi
Version: 0.0.36
Summary: Streamlit component for displaying KPI's
Author: Anthony Alteirac
Author-email: anthony@alteirac.com
Requires-Python: >=3.7
License-File: LICENSE
Requires-Dist: streamlit (>=1.2)
Requires-Dist: jinja2
